chunkcheck/__init__.py
chunkcheck/chunkcheck.py
chunkcheck-0.1.1.dist-info/WHEEL
chunkcheck-0.1.1.dist-info/METADATA
chunkcheck-0.1.1.dist-info/RECORD
