Metadata-Version: 2.4
Name: chunkcheck
Version: 0.1.1
Summary: Chunk and checkpoint memory optimisation
License-Expression: MIT
Requires-Dist: torch>=1.12
Requires-Python: >=3.9
